hexagonal/__init__.py
hexagonal/adapters/__init__.py
hexagonal/adapters/drivens/__init__.py
hexagonal/adapters/drivens/buses/__init__.py
hexagonal/adapters/drivens/buses/base/__init__.py
hexagonal/adapters/drivens/buses/base/command_bus.py
hexagonal/adapters/drivens/buses/base/event_bus.py
hexagonal/adapters/drivens/buses/base/infrastructure.py
hexagonal/adapters/drivens/buses/base/message_bus.py
hexagonal/adapters/drivens/buses/base/query.py
hexagonal/adapters/drivens/buses/base/utils.py
hexagonal/adapters/drivens/buses/inmemory/__init__.py
hexagonal/adapters/drivens/buses/inmemory/command_bus.py
hexagonal/adapters/drivens/buses/inmemory/event_bus.py
hexagonal/adapters/drivens/buses/inmemory/infra.py
hexagonal/adapters/drivens/mappers.py
hexagonal/adapters/drivens/repository/__init__.py
hexagonal/adapters/drivens/repository/base/__init__.py
hexagonal/adapters/drivens/repository/base/repository.py
hexagonal/adapters/drivens/repository/base/unit_of_work.py
hexagonal/adapters/drivens/repository/sqlalchemy/__init__.py
hexagonal/adapters/drivens/repository/sqlalchemy/datastore.py
hexagonal/adapters/drivens/repository/sqlalchemy/env_vars.py
hexagonal/adapters/drivens/repository/sqlalchemy/infrastructure.py
hexagonal/adapters/drivens/repository/sqlalchemy/models.py
hexagonal/adapters/drivens/repository/sqlalchemy/outbox.py
hexagonal/adapters/drivens/repository/sqlalchemy/repository.py
hexagonal/adapters/drivens/repository/sqlalchemy/unit_of_work.py
hexagonal/adapters/drivens/repository/sqlite/__init__.py
hexagonal/adapters/drivens/repository/sqlite/datastore.py
hexagonal/adapters/drivens/repository/sqlite/env_vars.py
hexagonal/adapters/drivens/repository/sqlite/infrastructure.py
hexagonal/adapters/drivens/repository/sqlite/outbox.py
hexagonal/adapters/drivens/repository/sqlite/repository.py
hexagonal/adapters/drivens/repository/sqlite/unit_of_work.py
hexagonal/adapters/drivers/__init__.py
hexagonal/adapters/drivers/app.py
hexagonal/application/__init__.py
python_hexagonal-0.1.2.dist-info/WHEEL
python_hexagonal-0.1.2.dist-info/METADATA
python_hexagonal-0.1.2.dist-info/RECORD
