Metadata-Version: 2.3
Name: python-hexagonal
Version: 0.1.2
Summary: Framework to build hexagonal architecture applications in Python.
Author: jose-matos-9281
Author-email: jose-matos-9281 <58991817+jose-matos-9281@users.noreply.github.com>
Requires-Dist: eventsourcing>=9.4.6
Requires-Dist: orjson>=3.11.5
Requires-Dist: pydantic>=2.12.5
Requires-Dist: sqlalchemy>=2.0.45
Requires-Dist: uuid6>=2025.0.1
Requires-Python: >=3.12
